lheplot/Analysis.py
lheplot/__init__.py
lheplot/lheplot.py
lheplot-0.0.1.dist-info/LICENSE
lheplot-0.0.1.dist-info/METADATA
lheplot-0.0.1.dist-info/WHEEL
lheplot-0.0.1.dist-info/entry_points.txt
lheplot-0.0.1.dist-info/top_level.txt
lheplot-0.0.1.dist-info/RECORD
