Metadata-Version: 2.1
Name: lheplot
Version: 0.0.1
Summary: A simple framework for plotting LHE files
Author-email: Karol Krizka <kkrizka@gmail.com>
Project-URL: Homepage, https://github.com/kkrizka/lheplot
Project-URL: Issues, https://github.com/kkrizka/lheplot/issues
Classifier: Programming Language :: Python :: 3
Classifier: License :: OSI Approved :: GNU General Public License v3 (GPLv3)
Classifier: Operating System :: OS Independent
License-File: LICENSE
Requires-Dist: awkward
Requires-Dist: hist
Requires-Dist: pylhe
Requires-Dist: uproot
